ghadiff-2.1.3.dist-info/licenses/LICENSE
workflow_compare/__init__.py
workflow_compare/api.py
workflow_compare/cli.py
workflow_compare/comparator.py
workflow_compare/reporter.py
ghadiff-2.1.3.dist-info/METADATA
ghadiff-2.1.3.dist-info/WHEEL
ghadiff-2.1.3.dist-info/entry_points.txt
ghadiff-2.1.3.dist-info/top_level.txt
ghadiff-2.1.3.dist-info/RECORD
