Metadata-Version: 2.4
Name: ghadiff
Version: 2.1.3
Summary: Compare GitHub workflow runs with detailed analysis
Author-email: Aswintechie <Aswintechie@users.noreply.github.com>
License: MIT
Project-URL: Homepage, https://github.com/Aswintechie/ghadiff
Project-URL: Repository, https://github.com/Aswintechie/ghadiff
Project-URL: Issues, https://github.com/Aswintechie/ghadiff/issues
Keywords: github,workflow,ci,comparison,analysis,gha,actions
Classifier: Development Status :: 4 - Beta
Classifier: Intended Audience :: Developers
Classifier: License :: OSI Approved :: MIT License
Classifier: Programming Language :: Python :: 3
Classifier: Programming Language :: Python :: 3.8
Classifier: Programming Language :: Python :: 3.9
Classifier: Programming Language :: Python :: 3.10
Classifier: Programming Language :: Python :: 3.11
Classifier: Programming Language :: Python :: 3.12
Classifier: Topic :: Software Development :: Build Tools
Classifier: Topic :: Software Development :: Quality Assurance
Requires-Python: >=3.8
License-File: LICENSE
Requires-Dist: requests>=2.25.0
Provides-Extra: dev
Requires-Dist: pytest>=7.0.0; extra == "dev"
Requires-Dist: pytest-cov>=4.0.0; extra == "dev"
Requires-Dist: black>=23.0.0; extra == "dev"
Requires-Dist: flake8>=6.0.0; extra == "dev"
Requires-Dist: mypy>=1.0.0; extra == "dev"
Dynamic: license-file
